LICENSE
MANIFEST.in
README.rst
setup.py
btl/__init__.py
btl/bitload.py
btl/utils.py
pybtl.egg-info/PKG-INFO
pybtl.egg-info/SOURCES.txt
pybtl.egg-info/dependency_links.txt
pybtl.egg-info/requires.txt
pybtl.egg-info/top_level.txt