Metadata-Version: 1.1
Name: pybtl
Version: 1.0.dev2
Summary: Library for serializing python objects as tightly packed bit arrays
Home-page: https://github.com/Outernet-Project/pybtl
Author: Outernet Inc
Author-email: apps@outernet.is
License: BSD
Keywords: binary serialization deserialization bits
Platform: UNKNOWN
Classifier: License :: OSI Approved :: BSD License
Classifier: Programming Language :: Python :: 2.7
Classifier: Programming Language :: Python :: 3
Classifier: Topic :: Utilities
